pdf_processing_lib/OLDjson_merger.py
pdf_processing_lib/OLDtsv_json_parser.py
pdf_processing_lib/__init__.py
pdf_processing_lib/image_processor.py
pdf_processing_lib/pdf_processor.py
pdf_processing_lib/text_extractor.py
pdf_processing_lib/tsvjson.py
pdf_processing_lib/utils.py
pdf_processing_lib-0.5.0.dist-info/LICENSE
pdf_processing_lib-0.5.0.dist-info/METADATA
pdf_processing_lib-0.5.0.dist-info/WHEEL
pdf_processing_lib-0.5.0.dist-info/top_level.txt
pdf_processing_lib-0.5.0.dist-info/RECORD
