Metadata-Version: 2.1
Name: pdf_processing_lib
Version: 0.5.0
Summary: A library for processing PDF documents, images, extracting text, parsing TSV to JSON, and merging JSON files
Home-page: https://github.com/yourusername/pdf_processing_lib
Author: Carlos Rosas
Author-email: crosashinostroza@gmail.com
Classifier: Programming Language :: Python :: 3
Classifier: License :: OSI Approved :: MIT License
Classifier: Operating System :: OS Independent
License-File: LICENSE
Requires-Dist: PyMuPDF
Requires-Dist: pdfplumber
Requires-Dist: joblib
Requires-Dist: tqdm
Requires-Dist: ultralytics
Requires-Dist: supervision
Requires-Dist: opencv-python
Requires-Dist: pandas
Requires-Dist: Pillow
